staticmap3/__init__.py
staticmap3/staticmap.py
staticmap3/tests.py
staticmap3-0.1.0.dist-info/LICENSE.txt
staticmap3-0.1.0.dist-info/METADATA
staticmap3-0.1.0.dist-info/WHEEL
staticmap3-0.1.0.dist-info/RECORD
