Metadata-Version: 2.3
Name: staticmap3
Version: 0.1.0
Summary: Fork of staticmap, a small, python-based library for creating map images with lines and markers.
License: Apache Software License
Keywords: static,map,image,osm
Author: Christoph Lingg
Author-email: christoph@komoot.de
Maintainer: SamR1
Requires-Python: >=3.9
Classifier: License :: OSI Approved :: Apache Software License
Classifier: Operating System :: POSIX :: Linux
Classifier: Programming Language :: Python :: 3
Classifier: Programming Language :: Python :: 3.9
Classifier: Programming Language :: Python :: 3.10
Classifier: Programming Language :: Python :: 3.11
Classifier: Programming Language :: Python :: 3.12
Classifier: Programming Language :: Python :: 3.13
Provides-Extra: dev
Provides-Extra: filecache
Requires-Dist: cachecontrol (>=0.14.3)
Requires-Dist: filelock (>=3.8.0) ; extra == "filecache"
Requires-Dist: mypy (>=1.15.0) ; extra == "dev"
Requires-Dist: pillow (>=11.2.1)
Requires-Dist: requests (>=2.32.3)
Requires-Dist: ruff (>=0.11.10) ; extra == "dev"
Requires-Dist: types-requests ; extra == "dev"
